setup.py
nest_distributions/Binomialdistribution.py
nest_distributions/Gaussiandistribution.py
nest_distributions/Generaldistribution.py
nest_distributions/__init__.py
nest_distributions.egg-info/PKG-INFO
nest_distributions.egg-info/SOURCES.txt
nest_distributions.egg-info/dependency_links.txt
nest_distributions.egg-info/not-zip-safe
nest_distributions.egg-info/top_level.txt