Metadata-Version: 1.0
Name: nest-distributions
Version: 0.5
Summary: Gaussian and Binomial distributions
Home-page: UNKNOWN
Author: Sachin Rai
Author-email: raisachin416@gmail.com
License: UNKNOWN
Platform: UNKNOWN
